pytube/__init__.py
pytube/main.py
pytube/classes/__init__.py
pytube/classes/downloader.py
pytube/classes/formatter.py
pytube/utils/__init__.py
pytube/utils/download_path.py
pytube/utils/env_handler.py
pytube_tool-0.1.2.dist-info/LICENSE.md
pytube_tool-0.1.2.dist-info/METADATA
pytube_tool-0.1.2.dist-info/WHEEL
pytube_tool-0.1.2.dist-info/entry_points.txt
pytube_tool-0.1.2.dist-info/top_level.txt
pytube_tool-0.1.2.dist-info/RECORD
