Metadata-Version: 2.1
Name: pytube-tool
Version: 0.1.2
Summary: A CLI tool to download YouTube Videos by giving an URL
Home-page: https://github.com/h471x/youtube_downloader
Author: Hatix Ntsoa
Author-email: hatixntsoa@gmail.com
License: MIT
Classifier: Programming Language :: Python :: 3
Classifier: License :: OSI Approved :: MIT License
Classifier: Operating System :: OS Independent
License-File: LICENSE.md
Requires-Dist: inquirer ==3.4.0
Requires-Dist: moviepy ==2.0.0.dev2
Requires-Dist: python-dotenv ==1.0.1
Requires-Dist: setuptools ==63.2.0
Requires-Dist: yt-dlp ==2024.11.18
